{"_type":"export","__export_format":4,"__export_date":"2021-08-23T20:38:21.105Z","__export_source":"insomnia.desktop.app:v2021.2.2","resources":[{"_id":"req_990ce2ce52ad471b9a85b79e14cde026","parentId":"fld_451f2a3a27724cddaa5bf2db1d63d149","modified":1629751072045,"created":1629750697028,"url":"{{ _.baseURL }}/account","name":"Create","description":"","method":"POST","body":{"mimeType":"application/json","text":"{\n\t\"cpf\": \"00000000000\",\n\t\"name\": \"Ayrton Souza\"\n}"},"parameters":[],"headers":[{"name":"Content-Type","value":"application/json","id":"pair_0fa20f88b2204f02bb3b7441343d1ad3"}],"authentication":{},"metaSortKey":-1629750697028,"isPrivate":false,"settingStoreCookies":true,"settingSendCookies":true,"settingDisableRenderRequestBody":false,"settingEncodeUrl":true,"settingRebuildPath":true,"settingFollowRedirects":"global","_type":"request"},{"_id":"fld_451f2a3a27724cddaa5bf2db1d63d149","parentId":"wrk_ac933febd72445eda67814ff629c76a9","modified":1629750664159,"created":1629750664159,"name":"Account","description":"","environment":{},"environmentPropertyOrder":null,"metaSortKey":-1629750664159,"_type":"request_group"},{"_id":"wrk_ac933febd72445eda67814ff629c76a9","parentId":null,"modified":1629750577387,"created":1629750577387,"name":"FinAPI","description":"","scope":"collection","_type":"workspace"},{"_id":"env_bab1c8e4988ff77792bac6addd57b9b22b9d9675","parentId":"wrk_ac933febd72445eda67814ff629c76a9","modified":1629750592432,"created":1629750577788,"name":"Base Environment","data":{"baseURL":"http://localhost:3333"},"dataPropertyOrder":{"&":["baseURL"]},"color":null,"isPrivate":false,"metaSortKey":1629750577788,"_type":"environment"},{"_id":"jar_bab1c8e4988ff77792bac6addd57b9b22b9d9675","parentId":"wrk_ac933febd72445eda67814ff629c76a9","modified":1629750577804,"created":1629750577804,"name":"Default Jar","cookies":[],"_type":"cookie_jar"},{"_id":"spc_e5796d75111b4bc9a3da887a73dab7a4","parentId":"wrk_ac933febd72445eda67814ff629c76a9","modified":1629750577398,"created":1629750577398,"fileName":"FinAPI","contents":"","contentType":"yaml","_type":"api_spec"},{"_id":"env_0e3a7e09c2f043ef91ce3c578040e8a1","parentId":"env_bab1c8e4988ff77792bac6addd57b9b22b9d9675","modified":1629750614782,"created":1629750598377,"name":"local","data":{"baseURL":"http://localhost:3333"},"dataPropertyOrder":{"&":["baseURL"]},"color":"#ab2eff","isPrivate":false,"metaSortKey":1629750598377,"_type":"environment"}]}